sa_package/__init__.py
sa_package/calendar/__init__.py
sa_package/calendar/calculate_date.py
sa_package/convert/__init__.py
sa_package/convert/datetime_format.py
sa_package/convert/number_format.py
sa_package/convert/time_format.py
sa_package/google_api/__init__.py
sa_package/google_api/gmail.py
sa_package/google_api/gspread.py
sa_package/google_api/my_gmail.py
sa_package/google_api/my_gspread.py
sa_package/google_api/my_youtube.py
sa_package/google_api/youtube.py
sa_package/my_selenium/__init__.py
sa_package/my_selenium/webdriver.py
sa_package/mydatabase/__init__.py
sa_package/mysql/__init__.py
sa_package/platform/__init__.py
sa_package/platform/afreecatv.py
sa_package/platform/google.py
sa_package/platform/slack.py
sa_package/platform/youtube.py
sa_package-0.0.80.dist-info/LICENSE
sa_package-0.0.80.dist-info/METADATA
sa_package-0.0.80.dist-info/WHEEL
sa_package-0.0.80.dist-info/top_level.txt
sa_package-0.0.80.dist-info/RECORD
