Metadata-Version: 2.1
Name: sa-package
Version: 0.0.80
Home-page: https://github.com/tmddk2709/sa_package
Author: Seunga Shin
Author-email: seungashin9275@gmail.com
License-File: LICENSE
Requires-Dist: bs4
Requires-Dist: pandas
Requires-Dist: gspread
Requires-Dist: oauth2client
Requires-Dist: google-api-python-client
Requires-Dist: google-auth-httplib2
Requires-Dist: google-auth-oauthlib
Requires-Dist: selenium
Requires-Dist: sqlalchemy (==1.4.45)
Requires-Dist: webdriver-manager
Requires-Dist: packaging
Requires-Dist: psycopg2-binary
Requires-Dist: pymysql
